{
  "id": "f8aa07d9-07d4-4000-87aa-98077567329d",
  "prevId": "f33993ed-c81a-4153-81cf-eebbd4e33d19",
  "version": "7",
  "dialect": "postgresql",
  "tables": {
    "public.anecdotes": {
      "name": "anecdotes",
      "schema": "",
      "columns": {
        "id": {
          "name": "id",
          "type": "serial",
          "primaryKey": true,
          "notNull": true
        },
        "content": {
          "name": "content",
          "type": "text",
          "primaryKey": false,
          "notNull": true
        },
        "topic": {
          "name": "topic",
          "type": "text",
          "primaryKey": false,
          "notNull": true
        },
        "votes": {
          "name": "votes",
          "type": "integer",
          "primaryKey": false,
          "notNull": true
        },
        "generated_with_ai": {
          "name": "generated_with_ai",
          "type": "boolean",
          "primaryKey": false,
          "notNull": true,
          "default": false
        },
        "created_at": {
          "name": "created_at",
          "type": "timestamp",
          "primaryKey": false,
          "notNull": true,
          "default": "now()"
        }
      },
      "indexes": {},
      "foreignKeys": {},
      "compositePrimaryKeys": {},
      "uniqueConstraints": {},
      "checkConstraints": {}
    }
  },
  "enums": {},
  "schemas": {},
  "sequences": {},
  "views": {},
  "_meta": {
    "columns": {},
    "schemas": {},
    "tables": {}
  }
}